<?xml version="1.0" encoding="utf-8"?>
<ConstraintsData xmlns:xsd="http://www.w3.org/2001/XMLSchema" xmlns:xsi="http://www.w3.org/2001/XMLSchema-instance">
  <FlattenedNetName2ConstraintNetId />
  <CNets />
  <CNetClasses />
  <CDifferentialPairs />
  <CDifferentialPairClasses />
  <CPinPairs />
  <CxSigClasses />
  <CxNets />
  <CXNetClasses />
  <ConstraintClearancesMatrix>
    <CCMFromScopes>
      <CCMFromScope Id="1f6e8272-18f5-4328-b2e7-8e4907fd2829">
        <ConstraintObject Id="00000000-0000-0000-0000-000000000000" />
        <CCMToScopes>
          <CCMToScope Id="72a17798-c74a-4dde-b46e-f764dd188a86" SetId="00000000-0000-0000-0000-000000000000">
            <ConstraintObject Id="00000000-0000-0000-0000-000000000000" />
            <DefaultConstraintClearancesMatrixConstraint Id="00000000-0000-0000-0000-000000000000" Kind="0" Name="" Description="" Scope1="" Scope2="" Attributes="" LayerType="0" LayerId="0" />
            <CCMConstraints />
          </CCMToScope>
        </CCMToScopes>
      </CCMFromScope>
    </CCMFromScopes>
  </ConstraintClearancesMatrix>
  <ConstraintSameNetClearancesMatrix>
    <CCMFromScopes />
  </ConstraintSameNetClearancesMatrix>
  <CSets />
  <CClearancesMatrixSets />
</ConstraintsData>